keycloak_manager/__init__.py
keycloak_manager/manager.py
keycloak_manager/models.py
keycloak_manager-0.1.3.dist-info/LICENSE
keycloak_manager-0.1.3.dist-info/METADATA
keycloak_manager-0.1.3.dist-info/WHEEL
keycloak_manager-0.1.3.dist-info/RECORD
