Metadata-Version: 2.1
Name: keycloak-manager
Version: 0.1.3
Summary: A simple Python package to work with Keycloak users and login systems
Home-page: https://github.com/anqorithm/keycloak-manager
License: MIT
Keywords: keycloak,authentication,user-management,tokens
Author: Abdullah Alqahtani
Author-email: abdullah@anqorithm.com
Requires-Python: >=3.12,<4.0
Classifier: Development Status :: 4 - Beta
Classifier: Intended Audience :: Developers
Classifier: License :: OSI Approved :: MIT License
Classifier: Programming Language :: Python :: 3
Classifier: Programming Language :: Python :: 3.12
Classifier: Topic :: Security
Classifier: Topic :: Software Development :: Libraries :: Python Modules
Requires-Dist: email-validator (>=2.2.0,<3.0.0)
Requires-Dist: faker (>=33.1.0,<34.0.0)
Requires-Dist: jwt (>=1.3.1,<2.0.0)
Requires-Dist: pydantic (>=2.10.4,<3.0.0)
Requires-Dist: pyjwt (>=2.10.1,<3.0.0)
Requires-Dist: requests (>=2.32.3,<3.0.0)
Project-URL: Repository, https://github.com/anqorithm/keycloak-manager
